docker_chrome_session_manager/__init__.py
docker_chrome_session_manager/data.py
docker_chrome_session_manager/manager.py
docker_chrome_session_manager-1.0.4.dist-info/LICENSE
docker_chrome_session_manager-1.0.4.dist-info/METADATA
docker_chrome_session_manager-1.0.4.dist-info/WHEEL
docker_chrome_session_manager-1.0.4.dist-info/RECORD
