Metadata-Version: 2.3
Name: docker-chrome-session-manager
Version: 1.0.4
Summary: A Python module for managing Selenium Chrome sessions across multiple Docker containers.
License: MIT License
Keywords: selenium,docker,chrome,session-manager
Author: FINWAX
Author-email: waxbid@gmail.com
Requires-Python: >=3.9
Classifier: Programming Language :: Python :: 3
Classifier: Programming Language :: Python :: 3.9
Classifier: Programming Language :: Python :: 3.10
Classifier: Programming Language :: Python :: 3.11
Classifier: Programming Language :: Python :: 3.12
Classifier: Programming Language :: Python :: 3.13
Classifier: License :: OSI Approved :: MIT License
Classifier: Operating System :: OS Independent
Requires-Dist: fake-useragent (>=2.2.0,<3.0.0)
Requires-Dist: filelock (>=3.18.0,<4.0.0)
Requires-Dist: requests (>=2.32.3,<3.0.0)
Requires-Dist: selenium (>=4.33.0,<5.0.0)
Project-URL: Homepage, https://github.com/FINWAX/docker-chrome-session-manager.py
Project-URL: Repository, https://github.com/FINWAX/docker-chrome-session-manager.py
